{
  "name": "Institucional/Saiba Mais",
  "path": "/i/saiba-mais",
  "sections": [
    {
      "__resolveType": "SEODefault"
    },
    {
      "__resolveType": "Default - Design System"
    },
    {
      "__resolveType": "HeaderFloating"
    },
    {
      "__resolveType": "site/sections/Container.tsx",
      "sections": [
        {
          "label": "Saiba Mais",
          "shadow": "none",
          "section": {
            "__resolveType": "site/sections/Institutional/PageContent.tsx",
            "title": "Saiba Mais",
            "asideMenu": {
              "__resolveType": "Aside Menu Global"
            },
            "content": {
              "__resolveType": "site/sections/Institutional/TextContent.tsx",
              "content": "<p style=\"list-style-type: none;\" data-mce-style=\"list-style-type: none;\"><a style=\"list-style-type: none;\" title=\"Sondas hospitalares: saiba o que são e qual a sua importância no dia a dia clínico\" href=\"/i/sondas-hospitalares-saiba-o-que-sao\" data-mce-linkchecker-status=\"valid\" data-mce-style=\"list-style-type: none;\" data-mce-href=\"../../../i/sondas-hospitalares-saiba-o-que-sao\" data-mce-selected=\"inline-boundary\">﻿Sondas hospitalares: saiba o que são e qual a sua importância no dia a dia clínico</a></p><p style=\"list-style-type: none;\" data-mce-style=\"list-style-type: none;\"><a style=\"list-style-type: none;\" title=\"Entenda o que é um aparelho de pressão e por que ele é tão importante no setor hospitalar\" href=\"https://www.hospitalardistribuidora.com.br/entenda-o-que-e-um-aparelho-de-pressao\" data-mce-linkchecker-status=\"valid\" data-mce-style=\"list-style-type: none;\" data-mce-href=\"https://www.hospitalardistribuidora.com.br/entenda-o-que-e-um-aparelho-de-pressao\">Entenda o que é um aparelho de pressão e por que ele é tão importante no setor hospitalar</a></p><p style=\"list-style-type: none;\" data-mce-style=\"list-style-type: none;\"><a style=\"list-style-type: none;\" title=\"Tudo o que você precisa saber sobre os equipos\" href=\"/i/saiba-o-que-sao-e-os-modelos-disponiveis-de-equipo\" data-mce-linkchecker-status=\"valid\" data-mce-style=\"list-style-type: none;\" data-mce-href=\"../../../i/saiba-o-que-sao-e-os-modelos-disponiveis-de-equipo\">Tudo o que você precisa saber sobre os equipos</a></p><p style=\"list-style-type: none;\" data-mce-style=\"list-style-type: none;\"><a style=\"list-style-type: none;\" title=\"Saiba a importância e os modelos de seringas que você precisa adquirir\" href=\"/i/saiba-a-importancia-e-os-modelos-de-seringas\" data-mce-linkchecker-status=\"valid\" data-mce-style=\"list-style-type: none;\" data-mce-href=\"../../../i/saiba-a-importancia-e-os-modelos-de-seringas\">Saiba a importância e os modelos de seringas que você precisa adquirir</a></p><p style=\"list-style-type: none;\" data-mce-style=\"list-style-type: none;\"><a style=\"list-style-type: none;\" title=\"Importância de contar com uma distribuidora hospitalar no interior de São Paulo\" href=\"/i/distribuidora-hospitalar-no-interior-de-sao-paulo\" data-mce-linkchecker-status=\"valid\" data-mce-style=\"list-style-type: none;\" data-mce-href=\"../../../i/distribuidora-hospitalar-no-interior-de-sao-paulo\">Importância de contar com uma distribuidora hospitalar no interior de São Paulo</a></p><p style=\"list-style-type: none;\" data-mce-style=\"list-style-type: none;\"><a style=\"list-style-type: none;\" title=\"Hospitalar: conheça a distribuidora de produtos hospitalares, medicamentos e materiais médicos em Presidente Prudente\" href=\"/i/distribuidora-produtos-hospitalares-medicamentos\" data-mce-linkchecker-status=\"valid\" data-mce-style=\"list-style-type: none;\" data-mce-href=\"../../../i/distribuidora-produtos-hospitalares-medicamentos\">Hospitalar: conheça a distribuidora de produtos hospitalares, medicamentos e materiais médicos em Presidente Prudente</a></p><p style=\"list-style-type: none;\" data-mce-style=\"list-style-type: none;\"><a style=\"list-style-type: none;\" title=\"Equipamentos médicos hospitalares\" href=\"/i/equipamentos-medicos-hospitalares\" data-mce-linkchecker-status=\"valid\" data-mce-style=\"list-style-type: none;\" data-mce-href=\"../../../i/equipamentos-medicos-hospitalares\">Equipamentos médicos hospitalares</a></p><p style=\"list-style-type: none;\" data-mce-style=\"list-style-type: none;\"><a style=\"list-style-type: none;\" title=\"Equipamentos médicos hospitalares para cirurgia ambulatorial\" href=\"/i/equipamentos-medicos-ambulatorial\" data-mce-linkchecker-status=\"valid\" data-mce-style=\"list-style-type: none;\" data-mce-href=\"../../../i/equipamentos-medicos-ambulatorial\">Equipamentos médicos hospitalares para cirurgia ambulatorial</a></p><p style=\"list-style-type: none;\" data-mce-style=\"list-style-type: none;\"><a style=\"list-style-type: none;\" title=\"Conheça alguns tipos de instrumentos cirúrgicos\" href=\"/i/conheca-alguns-tipos-de-instrumentos-cirurgicos\" data-mce-linkchecker-status=\"valid\" data-mce-style=\"list-style-type: none;\" data-mce-href=\"../../../i/conheca-alguns-tipos-de-instrumentos-cirurgicos\">Conheça alguns tipos de instrumentos cirúrgicos</a></p><p style=\"list-style-type: none;\" data-mce-style=\"list-style-type: none;\"><a style=\"list-style-type: none;\" title=\"Equipamentos médicos hospitalares\" href=\"/i/equipamentos-medicos-hospitalares\" data-mce-linkchecker-status=\"valid\" data-mce-style=\"list-style-type: none;\" data-mce-href=\"../../../i/equipamentos-medicos-hospitalares\">Equipamentos médicos hospitalares</a></p><p style=\"list-style-type: none;\" data-mce-style=\"list-style-type: none;\"><a style=\"list-style-type: none;\" title=\"Balança eletrônica para ambiente hospitalar\" href=\"/i/balanca-eletronica-para-ambiente-hospitalar\" data-mce-linkchecker-status=\"valid\" data-mce-style=\"list-style-type: none;\" data-mce-href=\"../../../i/balanca-eletronica-para-ambiente-hospitalar\">Balança eletrônica para ambiente hospitalar</a></p><p style=\"list-style-type: none;\" data-mce-style=\"list-style-type: none;\"><a style=\"list-style-type: none;\" title=\"Equipamentos médicos hospitalares para empresas de Home Care\" href=\"/i/equipamentos-medicos-home-care\" data-mce-linkchecker-status=\"valid\" data-mce-style=\"list-style-type: none;\" data-mce-href=\"../../../i/equipamentos-medicos-home-care\">Equipamentos médicos hospitalares para empresas de Home Care</a></p><p style=\"list-style-type: none;\" data-mce-style=\"list-style-type: none;\"><a style=\"list-style-type: none;\" title=\"Móveis hospitalares para consultório médico\" href=\"/i/moveis-hospitalares-para-consultorio-medico\" data-mce-linkchecker-status=\"valid\" data-mce-style=\"list-style-type: none;\" data-mce-href=\"../../../i/moveis-hospitalares-para-consultorio-medico\">Móveis hospitalares para consultório médico</a></p><p style=\"list-style-type: none;\" data-mce-style=\"list-style-type: none;\"><a style=\"list-style-type: none;\" title=\"O que é ambulatório interno de empresas\" href=\"/i/o-que-e-ambulatorio-interno-de-empresas\" data-mce-linkchecker-status=\"valid\" data-mce-style=\"list-style-type: none;\" data-mce-href=\"../../../i/o-que-e-ambulatorio-interno-de-empresas\">O que é ambulatório interno de empresas</a></p><p style=\"list-style-type: none;\" data-mce-style=\"list-style-type: none;\"><a style=\"list-style-type: none;\" title=\"Saiba qual a função do estetoscópio digital\" href=\"/i/saiba-qual-a-funcao-do-estetoscopio-digital\" data-mce-linkchecker-status=\"valid\" data-mce-style=\"list-style-type: none;\" data-mce-href=\"../../../i/saiba-qual-a-funcao-do-estetoscopio-digital\">Saiba qual a função do estetoscópio digital</a></p><p style=\"list-style-type: none;\" data-mce-style=\"list-style-type: none;\"><a style=\"list-style-type: none;\" title=\"Material médico para ambiente hospitalar\" href=\"/i/material-medico-para-ambiente-hospitalar\" data-mce-linkchecker-status=\"valid\" data-mce-style=\"list-style-type: none;\" data-mce-href=\"../../../i/material-medico-para-ambiente-hospitalar\">Material médico para ambiente hospitalar</a></p><p style=\"list-style-type: none;\" data-mce-style=\"list-style-type: none;\"><a style=\"list-style-type: none;\" title=\"As facilidades do aparelho de pressão digital G-Tech\" href=\"/i/facilidades-do-aparelho-de-pressao-digital-g-tech\" data-mce-linkchecker-status=\"valid\" data-mce-style=\"list-style-type: none;\" data-mce-href=\"../../../i/facilidades-do-aparelho-de-pressao-digital-g-tech\">As facilidades do aparelho de pressão digital G-Tech</a></p><p style=\"list-style-type: none;\" data-mce-style=\"list-style-type: none;\"><a style=\"list-style-type: none;\" title=\"Equipamentos para ambulatório de especialidades\" href=\"/i/equipamentos-para-ambulatorio-de-especialidades\" data-mce-linkchecker-status=\"valid\" data-mce-style=\"list-style-type: none;\" data-mce-href=\"../../../i/equipamentos-para-ambulatorio-de-especialidades\">Equipamentos para ambulatório de especialidades</a></p><p style=\"list-style-type: none;\" data-mce-style=\"list-style-type: none;\"><a style=\"list-style-type: none;\" title=\"Pinças hemostáticas para procedimento cirúrgico\" href=\"/i/pincas-hemostaticas-para-procedimento-cirurgico\" data-mce-linkchecker-status=\"valid\" data-mce-style=\"list-style-type: none;\" data-mce-href=\"../../../i/pincas-hemostaticas-para-procedimento-cirurgico\">Pinças hemostáticas para procedimento cirúrgico</a></p><p style=\"list-style-type: none;\" data-mce-style=\"list-style-type: none;\"><a style=\"list-style-type: none;\" title=\"Inaladores e nebulizadores: saiba qual a importância destes aparelhos\" href=\"/i/inaladores-e-nebulizadores-importancia\" data-mce-linkchecker-status=\"valid\" data-mce-style=\"list-style-type: none;\" data-mce-href=\"../../../i/inaladores-e-nebulizadores-importancia\">Inaladores e nebulizadores: saiba qual a importância destes aparelhos</a></p><p style=\"list-style-type: none;\" data-mce-style=\"list-style-type: none;\"><a style=\"list-style-type: none;\" title=\"Conheça alguns tipos de sonda hospitalar\" href=\"/i/conheca-alguns-tipos-de-sonda-hospitalar\" data-mce-linkchecker-status=\"valid\" data-mce-style=\"list-style-type: none;\" data-mce-href=\"../../../i/conheca-alguns-tipos-de-sonda-hospitalar\">Conheça alguns tipos de sonda hospitalar</a></p><p style=\"list-style-type: none;\" data-mce-style=\"list-style-type: none;\"><a style=\"list-style-type: none;\" title=\"Conheça a função do oftalmoscópio\" href=\"/i/conheca-a-funcao-do-oftalmoscopio\" data-mce-linkchecker-status=\"valid\" data-mce-style=\"list-style-type: none;\" data-mce-href=\"../../../i/conheca-a-funcao-do-oftalmoscopio\">Conheça a função do oftalmoscópio</a></p><p style=\"list-style-type: none;\" data-mce-style=\"list-style-type: none;\"><a style=\"list-style-type: none;\" title=\"Aparelho medidor de glicose\" href=\"/i/aparelho-medidor-de-glicose\" data-mce-linkchecker-status=\"valid\" data-mce-style=\"list-style-type: none;\" data-mce-href=\"../../../i/aparelho-medidor-de-glicose\">Aparelho medidor de glicose</a></p><p style=\"list-style-type: none;\" data-mce-style=\"list-style-type: none;\"><a style=\"list-style-type: none;\" title=\"Artigos hospitalares em Presidente Prudente\" href=\"/i/artigos-hospitalares-em-presidente-prudente\" data-mce-linkchecker-status=\"valid\" data-mce-style=\"list-style-type: none;\" data-mce-href=\"../../../i/artigos-hospitalares-em-presidente-prudente\">Artigos hospitalares em Presidente Prudente</a></p><p style=\"list-style-type: none;\" data-mce-style=\"list-style-type: none;\"><a style=\"list-style-type: none;\" title=\"Comprar artigos hospitalares online\" href=\"/i/comprar-artigos-hospitalares-online\" data-mce-linkchecker-status=\"valid\" data-mce-style=\"list-style-type: none;\" data-mce-href=\"../../../i/comprar-artigos-hospitalares-online\">Comprar artigos hospitalares online</a></p><p style=\"list-style-type: none;\" data-mce-style=\"list-style-type: none;\"><a style=\"list-style-type: none;\" title=\"Tipos de fios cirúrgicos\" href=\"/i/tipos-de-fios-cirurgicos\" data-mce-linkchecker-status=\"valid\" data-mce-style=\"list-style-type: none;\" data-mce-href=\"../../../i/tipos-de-fios-cirurgicos\">Tipos de fios cirúrgicos</a></p><p style=\"list-style-type: none;\" data-mce-style=\"list-style-type: none;\"><a style=\"list-style-type: none;\" title=\"Por que comprar uma balança antropométrica?\" href=\"/i/por-que-comprar-uma-balanca-antropometrica\" data-mce-linkchecker-status=\"valid\" data-mce-style=\"list-style-type: none;\" data-mce-href=\"../../../i/por-que-comprar-uma-balanca-antropometrica\">Por que comprar uma balança antropométrica?</a></p><p style=\"list-style-type: none;\" data-mce-style=\"list-style-type: none;\"><a style=\"list-style-type: none;\" title=\"O que faz uma distribuidora de medicamentos?\" href=\"/i/o-que-faz-uma-distribuidora-de-medicamentos\" data-mce-linkchecker-status=\"valid\" data-mce-style=\"list-style-type: none;\" data-mce-href=\"../../../i/o-que-faz-uma-distribuidora-de-medicamentos\">O que faz uma distribuidora de medicamentos?</a></p><p style=\"list-style-type: none;\" data-mce-style=\"list-style-type: none;\"><a style=\"list-style-type: none;\" title=\"Como montar um kit de enfermagem completo\" href=\"/i/como-montar-um-kit-de-enfermagem-completo\" data-mce-linkchecker-status=\"valid\" data-mce-style=\"list-style-type: none;\" data-mce-href=\"../../../i/como-montar-um-kit-de-enfermagem-completo\">Como montar um kit de enfermagem completo</a></p><p style=\"list-style-type: none;\" data-mce-style=\"list-style-type: none;\"><a style=\"list-style-type: none;\" title=\"Por que usar material cirúrgico descartável\" href=\"/i/por-que-usar-material-cirurgico-descartavel\" data-mce-linkchecker-status=\"valid\" data-mce-style=\"list-style-type: none;\" data-mce-href=\"../../../i/por-que-usar-material-cirurgico-descartavel\">Por que usar material cirúrgico descartável</a></p><p style=\"list-style-type: none;\" data-mce-style=\"list-style-type: none;\"><a style=\"list-style-type: none;\" title=\"Estufa para esterilização de material médico hospitalar\" href=\"/i/estufa-esterilizacao-material-medico-hospitalar\" data-mce-linkchecker-status=\"valid\" data-mce-style=\"list-style-type: none;\" data-mce-href=\"../../../i/estufa-esterilizacao-material-medico-hospitalar\">Estufa para esterilização de material médico hospitalar</a></p><p style=\"list-style-type: none;\" data-mce-style=\"list-style-type: none;\"><a style=\"list-style-type: none;\" title=\"Material para punção venosa\" href=\"/i/material-para-puncao-venosa\" data-mce-linkchecker-status=\"valid\" data-mce-style=\"list-style-type: none;\" data-mce-href=\"../../../i/material-para-puncao-venosa\">Material para punção venosa</a></p><p style=\"list-style-type: none;\" data-mce-style=\"list-style-type: none;\"><a style=\"list-style-type: none;\" title=\"Colchão hospitalar: saiba quais as características especiais\" href=\"/i/colchao-hospitalar-caracteristicas-especiais\" data-mce-linkchecker-status=\"valid\" data-mce-style=\"list-style-type: none;\" data-mce-href=\"../../../i/colchao-hospitalar-caracteristicas-especiais\">Colchão hospitalar: saiba quais as características especiais</a></p><p style=\"list-style-type: none;\" data-mce-style=\"list-style-type: none;\"><a style=\"list-style-type: none;\" title=\"Seringa de insulina: cuidados importantes\" href=\"/i/seringa-de-insulina-cuidados-importantes\" data-mce-linkchecker-status=\"valid\" data-mce-style=\"list-style-type: none;\" data-mce-href=\"../../../i/seringa-de-insulina-cuidados-importantes\">Seringa de insulina: cuidados importantes</a></p><p style=\"list-style-type: none;\" data-mce-style=\"list-style-type: none;\"><a style=\"list-style-type: none;\" title=\"Cadeira de banho para idoso\" href=\"/i/cadeira-de-banho-para-idoso\" data-mce-linkchecker-status=\"valid\" data-mce-style=\"list-style-type: none;\" data-mce-href=\"../../../i/cadeira-de-banho-para-idoso\">Cadeira de banho para idoso</a></p><p style=\"list-style-type: none;\" data-mce-style=\"list-style-type: none;\"><a style=\"list-style-type: none;\" title=\"Pra que serve o desfibrilador externo automático e manual?\" href=\"/i/desfibrilador-externo-automatico-e-manual\" data-mce-linkchecker-status=\"valid\" data-mce-style=\"list-style-type: none;\" data-mce-href=\"../../../i/desfibrilador-externo-automatico-e-manual\">Pra que serve o desfibrilador externo automático e manual?</a></p><p style=\"list-style-type: none;\" data-mce-style=\"list-style-type: none;\"><a style=\"list-style-type: none;\" title=\"Conheça alguns modelos de cadeira de rodas\" href=\"/i/conheca-alguns-modelos-de-cadeira-de-rodas\" data-mce-linkchecker-status=\"valid\" data-mce-style=\"list-style-type: none;\" data-mce-href=\"../../../i/conheca-alguns-modelos-de-cadeira-de-rodas\">Conheça alguns modelos de cadeira de rodas</a></p><p style=\"list-style-type: none;\" data-mce-style=\"list-style-type: none;\"><a style=\"list-style-type: none;\" title=\"Pressão alta em crianças\" href=\"/i/pressao-alta-em-criancas\" data-mce-linkchecker-status=\"valid\" data-mce-style=\"list-style-type: none;\" data-mce-href=\"../../../i/pressao-alta-em-criancas\">Pressão alta em crianças</a></p><p style=\"list-style-type: none;\" data-mce-style=\"list-style-type: none;\"><a style=\"list-style-type: none;\" title=\"Lavadora ultrassônica para hospitais\" href=\"/i/lavadora-ultrassonica-para-hospitais\" data-mce-linkchecker-status=\"valid\" data-mce-style=\"list-style-type: none;\" data-mce-href=\"../../../i/lavadora-ultrassonica-para-hospitais\">Lavadora ultrassônica para hospitais</a></p><p style=\"list-style-type: none;\" data-mce-style=\"list-style-type: none;\"><a style=\"list-style-type: none;\" title=\"Materiais para coleta de sangue a vácuo\" href=\"/i/materiais-para-coleta-de-sangue-a-vacuo\" data-mce-linkchecker-status=\"valid\" data-mce-style=\"list-style-type: none;\" data-mce-href=\"../../../i/materiais-para-coleta-de-sangue-a-vacuo\">Materiais para coleta de sangue a vácuo</a></p><p style=\"list-style-type: none;\" data-mce-style=\"list-style-type: none;\"><a style=\"list-style-type: none;\" title=\"Coleta de sangue: passo a passo\" href=\"/i/coleta-de-sangue-passo-a-passo\" data-mce-linkchecker-status=\"valid\" data-mce-style=\"list-style-type: none;\" data-mce-href=\"../../../i/coleta-de-sangue-passo-a-passo\">Coleta de sangue: passo a passo</a></p><p style=\"list-style-type: none;\" data-mce-style=\"list-style-type: none;\"><a style=\"list-style-type: none;\" title=\"O que são saneantes hospitalares?\" href=\"/i/o-que-sao-saneantes-hospitalares\" data-mce-linkchecker-status=\"valid\" data-mce-style=\"list-style-type: none;\" data-mce-href=\"../../../i/o-que-sao-saneantes-hospitalares\">O que são saneantes hospitalares?</a></p><p style=\"list-style-type: none;\" data-mce-style=\"list-style-type: none;\"><a style=\"list-style-type: none;\" title=\"Por que os tubos para coleta de sangue têm tampa colorida?\" href=\"/i/tubos-para-coleta-de-sangue-tem-tampa-colorida\" data-mce-linkchecker-status=\"valid\" data-mce-style=\"list-style-type: none;\" data-mce-href=\"../../../i/tubos-para-coleta-de-sangue-tem-tampa-colorida\">Por que os tubos para coleta de sangue têm tampa colorida?</a></p><p style=\"list-style-type: none;\" data-mce-style=\"list-style-type: none;\"><a style=\"list-style-type: none;\" title=\"Uso da seringa descartável em ambiente hospitalar\" href=\"/i/uso-da-seringa-descartavel-em-ambiente-hospitalar\" data-mce-linkchecker-status=\"valid\" data-mce-style=\"list-style-type: none;\" data-mce-href=\"../../../i/uso-da-seringa-descartavel-em-ambiente-hospitalar\">Uso da seringa descartável em ambiente hospitalar</a></p><p style=\"list-style-type: none;\" data-mce-style=\"list-style-type: none;\"><a style=\"list-style-type: none;\" title=\"Saiba quais os passos da administração de medicamentos\" href=\"/i/passos-da-administracao-de-medicamentos\" data-mce-linkchecker-status=\"valid\" data-mce-style=\"list-style-type: none;\" data-mce-href=\"../../../i/passos-da-administracao-de-medicamentos\">Saiba quais os passos da administração de medicamentos</a></p><p style=\"list-style-type: none;\" data-mce-style=\"list-style-type: none;\"><a style=\"list-style-type: none;\" title=\"Importância do material hospitalar descartável\" href=\"/i/importancia-do-material-hospitalar-descartavel\" data-mce-linkchecker-status=\"valid\" data-mce-style=\"list-style-type: none;\" data-mce-href=\"../../../i/importancia-do-material-hospitalar-descartavel\">Importância do material hospitalar descartável</a></p><p style=\"list-style-type: none;\" data-mce-style=\"list-style-type: none;\"><a style=\"list-style-type: none;\" title=\"Para que serve Voltaren?\" href=\"/i/para-que-serve-voltaren\" data-mce-linkchecker-status=\"valid\" data-mce-style=\"list-style-type: none;\" data-mce-href=\"../../../i/para-que-serve-voltaren\">Para que serve Voltaren?</a></p><p style=\"list-style-type: none;\" data-mce-style=\"list-style-type: none;\"><a style=\"list-style-type: none;\" title=\"Material médico em Presidente Prudente\" href=\"/i/material-medico-em-presidente-prudente\" data-mce-linkchecker-status=\"valid\" data-mce-style=\"list-style-type: none;\" data-mce-href=\"../../../i/material-medico-em-presidente-prudente\">Material médico em Presidente Prudente</a></p><p style=\"list-style-type: none;\" data-mce-style=\"list-style-type: none;\"><a style=\"list-style-type: none;\" title=\"Conheça alguns tipos de cateter usados na enfermagem\" href=\"/i/tipos-de-cateter-usados-na-enfermagem\" data-mce-linkchecker-status=\"valid\" data-mce-style=\"list-style-type: none;\" data-mce-href=\"../../../i/tipos-de-cateter-usados-na-enfermagem\">Conheça alguns tipos de cateter usados na enfermagem</a></p><p style=\"list-style-type: none;\" data-mce-style=\"list-style-type: none;\"><a style=\"list-style-type: none;\" title=\"O que é gestão hospitalar?\" href=\"/i/o-que-e-gestao-hospitalar\" data-mce-linkchecker-status=\"valid\" data-mce-style=\"list-style-type: none;\" data-mce-href=\"../../../i/o-que-e-gestao-hospitalar\">O que é gestão hospitalar?</a></p><p style=\"list-style-type: none;\" data-mce-style=\"list-style-type: none;\"><a style=\"list-style-type: none;\" title=\"Controle de infecção hospitalar: importância e cuidados\" href=\"/i/controle-infeccao-hospitalar-importancia-e-cuidado\" data-mce-linkchecker-status=\"valid\" data-mce-style=\"list-style-type: none;\" data-mce-href=\"../../../i/controle-infeccao-hospitalar-importancia-e-cuidado\">Controle de infecção hospitalar: importância e cuidados</a></p><p style=\"list-style-type: none;\" data-mce-style=\"list-style-type: none;\"><a style=\"list-style-type: none;\" title=\"Produtos hospitalares\" href=\"/i/produtos-hospitalares\" data-mce-linkchecker-status=\"valid\" data-mce-style=\"list-style-type: none;\" data-mce-href=\"../../../i/produtos-hospitalares\">Produtos hospitalares</a></p><p style=\"list-style-type: none;\" data-mce-style=\"list-style-type: none;\"><a style=\"list-style-type: none;\" title=\"Materiais de curativo\" href=\"/i/materiais-de-curativo\" data-mce-linkchecker-status=\"valid\" data-mce-style=\"list-style-type: none;\" data-mce-href=\"../../../i/materiais-de-curativo\">Materiais de curativo</a></p><p style=\"list-style-type: none;\" data-mce-style=\"list-style-type: none;\"><a style=\"list-style-type: none;\" title=\"Limpeza hospitalar\" href=\"/i/limpeza-hospitalar\" data-mce-linkchecker-status=\"valid\" data-mce-style=\"list-style-type: none;\" data-mce-href=\"../../../i/limpeza-hospitalar\">Limpeza hospitalar</a></p><p style=\"list-style-type: none;\" data-mce-style=\"list-style-type: none;\"><a style=\"list-style-type: none;\" title=\"Instrumentos cirúrgicos\" href=\"/i/instrumentos-cirurgicos\" data-mce-linkchecker-status=\"valid\" data-mce-style=\"list-style-type: none;\" data-mce-href=\"../../../i/instrumentos-cirurgicos\">Instrumentos cirúrgicos</a></p><p style=\"list-style-type: none;\" data-mce-style=\"list-style-type: none;\"><a style=\"list-style-type: none;\" title=\"Para que serve colar cervical\" href=\"/i/para-que-serve-colar-cervical\" data-mce-linkchecker-status=\"valid\" data-mce-style=\"list-style-type: none;\" data-mce-href=\"../../../i/para-que-serve-colar-cervical\">Para que serve colar cervical</a></p><p style=\"list-style-type: none;\" data-mce-style=\"list-style-type: none;\"><a style=\"list-style-type: none;\" title=\"Conheça os tipos de sonda nasogástrica\" href=\"/i/conheca-os-tipos-de-sonda-nasogastrica\" data-mce-linkchecker-status=\"valid\" data-mce-style=\"list-style-type: none;\" data-mce-href=\"../../../i/conheca-os-tipos-de-sonda-nasogastrica\">Conheça os tipos de sonda nasogástrica</a></p><p style=\"list-style-type: none;\" data-mce-style=\"list-style-type: none;\"><a style=\"list-style-type: none;\" title=\"Conheça 3 equipamentos médicos para consultório\" href=\"/i/conheca-3-equipamentos-medicos-para-consultorio\" data-mce-linkchecker-status=\"valid\" data-mce-style=\"list-style-type: none;\" data-mce-href=\"../../../i/conheca-3-equipamentos-medicos-para-consultorio\">Conheça 3 equipamentos médicos para consultório</a></p><p style=\"list-style-type: none;\" data-mce-style=\"list-style-type: none;\"><a style=\"list-style-type: none;\" title=\"Qual a importância da roupa cirúrgica\" href=\"/i/qual-a-importancia-da-roupa-cirurgica\" data-mce-linkchecker-status=\"valid\" data-mce-style=\"list-style-type: none;\" data-mce-href=\"../../../i/qual-a-importancia-da-roupa-cirurgica\">Qual a importância da roupa cirúrgica</a></p><p style=\"list-style-type: none;\" data-mce-style=\"list-style-type: none;\"><a style=\"list-style-type: none;\" title=\"Saiba quais os tipos e função de cada cama hospitalar\" href=\"/i/saiba-quais-tipos-e-funcao-de-cada-cama-hospitalar\" data-mce-linkchecker-status=\"valid\" data-mce-style=\"list-style-type: none;\" data-mce-href=\"../../../i/saiba-quais-tipos-e-funcao-de-cada-cama-hospitalar\">Saiba quais os tipos e função de cada cama hospitalar</a></p><p style=\"list-style-type: none;\" data-mce-style=\"list-style-type: none;\"><a style=\"list-style-type: none;\" title=\"Conheça os tipos de fio de sutura\" href=\"/i/conheca-os-tipos-de-fio-de-sutura\" data-mce-linkchecker-status=\"valid\" data-mce-style=\"list-style-type: none;\" data-mce-href=\"../../../i/conheca-os-tipos-de-fio-de-sutura\">Conheça os tipos de fio de sutura</a></p><p style=\"list-style-type: none;\" data-mce-style=\"list-style-type: none;\"><a style=\"list-style-type: none;\" title=\"EPI hospitalar: materiais importantes para segurança no trabalho\" href=\"/i/epi-hospitalar-materiais-seguranca-no-trabalho\" data-mce-linkchecker-status=\"valid\" data-mce-style=\"list-style-type: none;\" data-mce-href=\"../../../i/epi-hospitalar-materiais-seguranca-no-trabalho\">EPI hospitalar: materiais importantes para segurança no trabalho</a></p><p style=\"list-style-type: none;\" data-mce-style=\"list-style-type: none;\"><a style=\"list-style-type: none;\" title=\"Descarte de lixo hospitalar\" href=\"/i/descarte-de-lixo-hospitalar\" data-mce-linkchecker-status=\"valid\" data-mce-style=\"list-style-type: none;\" data-mce-href=\"../../../i/descarte-de-lixo-hospitalar\">Descarte de lixo hospitalar</a></p><p style=\"list-style-type: none;\" data-mce-style=\"list-style-type: none;\"><a style=\"list-style-type: none;\" title=\"Por que fazer ultrassom com doppler fetal?\" href=\"/i/por-que-fazer-ultrassom-com-doppler-fetal\" data-mce-linkchecker-status=\"valid\" data-mce-style=\"list-style-type: none;\" data-mce-href=\"../../../i/por-que-fazer-ultrassom-com-doppler-fetal\">Por que fazer ultrassom com doppler fetal?</a></p><p style=\"list-style-type: none;\" data-mce-style=\"list-style-type: none;\"><a style=\"list-style-type: none;\" title=\"Equipamentos para fisioterapia: conheça a função de alguns\" href=\"/i/equipamentos-para-fisioterapia-conheca-a-funcao\" data-mce-linkchecker-status=\"valid\" data-mce-style=\"list-style-type: none;\" data-mce-href=\"../../../i/equipamentos-para-fisioterapia-conheca-a-funcao\">Equipamentos para fisioterapia: conheça a função de alguns</a></p><p style=\"list-style-type: none;\" data-mce-style=\"list-style-type: none;\"><a style=\"list-style-type: none;\" title=\"Quais as melhores marcas de estetoscópio?\" href=\"/i/quais-as-melhores-marcas-de-estetoscopio\" data-mce-linkchecker-status=\"valid\" data-mce-style=\"list-style-type: none;\" data-mce-href=\"../../../i/quais-as-melhores-marcas-de-estetoscopio\">Quais as melhores marcas de estetoscópio?</a></p><p style=\"list-style-type: none;\" data-mce-style=\"list-style-type: none;\"><a style=\"list-style-type: none;\" title=\"Estetoscópio infantil: dicas para fazer a melhor compra\" href=\"/i/estetoscopio-infantil-dicas-para-a-melhor-compra\" data-mce-linkchecker-status=\"valid\" data-mce-style=\"list-style-type: none;\" data-mce-href=\"../../../i/estetoscopio-infantil-dicas-para-a-melhor-compra\">Estetoscópio infantil: dicas para fazer a melhor compra</a></p><p style=\"list-style-type: none;\" data-mce-style=\"list-style-type: none;\"><a style=\"list-style-type: none;\" title=\"6 dicas para você escolher a melhor autoclave odontológica\" href=\"/i/dicas-para-escolher-melhor-autoclave-odontologica\" data-mce-linkchecker-status=\"valid\" data-mce-style=\"list-style-type: none;\" data-mce-href=\"../../../i/dicas-para-escolher-melhor-autoclave-odontologica\">6 dicas para você escolher a melhor autoclave odontológica</a></p><p style=\"list-style-type: none;\" data-mce-style=\"list-style-type: none;\"><a style=\"list-style-type: none;\" title=\"Qual a melhor marca de oxímetro de dedo?\" href=\"/i/qual-a-melhor-marca-de-oximetro-de-dedo\" data-mce-linkchecker-status=\"valid\" data-mce-style=\"list-style-type: none;\" data-mce-href=\"../../../i/qual-a-melhor-marca-de-oximetro-de-dedo\">Qual a melhor marca de oxímetro de dedo?</a></p><p style=\"list-style-type: none;\" data-mce-style=\"list-style-type: none;\"><a style=\"list-style-type: none;\" title=\"Bomba para tirar leite materno: saiba como escolher uma perfeita\" href=\"/i/bomba-para-tirar-leite-materno-saiba-como-escolher\" data-mce-linkchecker-status=\"valid\" data-mce-style=\"list-style-type: none;\" data-mce-href=\"../../../i/bomba-para-tirar-leite-materno-saiba-como-escolher\">Bomba para tirar leite materno: saiba como escolher uma perfeita</a></p><p style=\"list-style-type: none;\" data-mce-style=\"list-style-type: none;\"><a style=\"list-style-type: none;\" title=\"Como funciona uma farmácia hospitalar?\" href=\"/i/como-funciona-uma-farmacia-hospitalar\" data-mce-linkchecker-status=\"valid\" data-mce-style=\"list-style-type: none;\" data-mce-href=\"../../../i/como-funciona-uma-farmacia-hospitalar\">Como funciona uma farmácia hospitalar?</a></p><p style=\"list-style-type: none;\" data-mce-style=\"list-style-type: none;\"><a style=\"list-style-type: none;\" title=\"Principais instrumentos usados em procedimentos cirúrgicos\" href=\"/i/principais-instrumentos-procedimentos-cirurgicos\" data-mce-linkchecker-status=\"valid\" data-mce-style=\"list-style-type: none;\" data-mce-href=\"../../../i/principais-instrumentos-procedimentos-cirurgicos\">Principais instrumentos usados em procedimentos cirúrgicos</a></p><p style=\"list-style-type: none;\" data-mce-style=\"list-style-type: none;\"><a style=\"list-style-type: none;\" title=\"Conheça cinco equipamentos de primeiros socorros\" href=\"/i/conheca-cinco-equipamentos-de-primeiros-socorros\" data-mce-linkchecker-status=\"valid\" data-mce-style=\"list-style-type: none;\" data-mce-href=\"../../../i/conheca-cinco-equipamentos-de-primeiros-socorros\">Conheça cinco equipamentos de primeiros socorros</a></p><p style=\"list-style-type: none;\" data-mce-style=\"list-style-type: none;\"><a style=\"list-style-type: none;\" title=\"Conheça os tipos de estetoscópio Spirit\" href=\"/i/conheca-os-tipos-de-estetoscopio-spirit\" data-mce-linkchecker-status=\"valid\" data-mce-style=\"list-style-type: none;\" data-mce-href=\"../../../i/conheca-os-tipos-de-estetoscopio-spirit\">Conheça os tipos de estetoscópio Spirit</a></p><p style=\"list-style-type: none;\" data-mce-style=\"list-style-type: none;\"><a style=\"list-style-type: none;\" title=\"Estetoscópio Spirit é bom?\" href=\"/i/estetoscopio-spirit-e-bom\" data-mce-linkchecker-status=\"valid\" data-mce-style=\"list-style-type: none;\" data-mce-href=\"../../../i/estetoscopio-spirit-e-bom\">Estetoscópio Spirit é bom?</a></p><p style=\"list-style-type: none;\" data-mce-style=\"list-style-type: none;\"><a style=\"list-style-type: none;\" title=\"Cateter intravenoso: conheça os tipos\" href=\"/i/cateter-intravenoso-conheca-os-tipos\" data-mce-linkchecker-status=\"valid\" data-mce-style=\"list-style-type: none;\" data-mce-href=\"../../../i/cateter-intravenoso-conheca-os-tipos\">Cateter intravenoso: conheça os tipos</a></p><p style=\"list-style-type: none;\" data-mce-style=\"list-style-type: none;\"><a style=\"list-style-type: none;\" title=\"Coleta de sangue a vácuo: quais materiais usar?\" href=\"/i/coleta-de-sangue-a-vacuo-quais-materiais-usar\" data-mce-linkchecker-status=\"valid\" data-mce-style=\"list-style-type: none;\" data-mce-href=\"../../../i/coleta-de-sangue-a-vacuo-quais-materiais-usar\">Coleta de sangue a vácuo: quais materiais usar?</a></p><p style=\"list-style-type: none;\" data-mce-style=\"list-style-type: none;\"><a style=\"list-style-type: none;\" title=\"Tipos de pinças cirúrgicas\" href=\"/i/tipos-de-pincas-cirurgicas\" data-mce-linkchecker-status=\"valid\" data-mce-style=\"list-style-type: none;\" data-mce-href=\"../../../i/tipos-de-pincas-cirurgicas\">Tipos de pinças cirúrgicas</a></p><p style=\"list-style-type: none;\" data-mce-style=\"list-style-type: none;\"><a style=\"list-style-type: none;\" title=\"Cama hospitalar: quais os tipos e as características\" href=\"/i/cama-hospitalar-quais-os-tipos-e-as-caracteristica\" data-mce-linkchecker-status=\"valid\" data-mce-style=\"list-style-type: none;\" data-mce-href=\"../../../i/cama-hospitalar-quais-os-tipos-e-as-caracteristica\">Cama hospitalar: quais os tipos e as características</a></p><p style=\"list-style-type: none;\" data-mce-style=\"list-style-type: none;\"><a style=\"list-style-type: none;\" title=\"Umidificador de ambiente: como escolher o melhor?\" href=\"/i/umidificador-de-ambiente-como-escolher-o-melhor\" data-mce-linkchecker-status=\"valid\" data-mce-style=\"list-style-type: none;\" data-mce-href=\"../../../i/umidificador-de-ambiente-como-escolher-o-melhor\">Umidificador de ambiente: como escolher o melhor?</a></p><p style=\"list-style-type: none;\" data-mce-style=\"list-style-type: none;\"><a style=\"list-style-type: none;\" title=\"Conheça os tipos de luvas de procedimento\" href=\"/i/conheca-os-tipos-de-luvas-de-procedimento\" data-mce-linkchecker-status=\"valid\" data-mce-style=\"list-style-type: none;\" data-mce-href=\"../../../i/conheca-os-tipos-de-luvas-de-procedimento\">Conheça os tipos de luvas de procedimento</a></p><p style=\"list-style-type: none;\" data-mce-style=\"list-style-type: none;\"><a style=\"list-style-type: none;\" title=\"Medidor de diabetes: dicas para comprar o certo\" href=\"/i/medidor-de-diabetes-dicas-para-comprar-o-certo\" data-mce-linkchecker-status=\"valid\" data-mce-style=\"list-style-type: none;\" data-mce-href=\"../../../i/medidor-de-diabetes-dicas-para-comprar-o-certo\">Medidor de diabetes: dicas para comprar o certo</a></p><p style=\"list-style-type: none;\" data-mce-style=\"list-style-type: none;\"><a style=\"list-style-type: none;\" title=\"Pomada xilocaína: principais usos\" href=\"/i/pomada-xilocaina-principais-usos\" data-mce-linkchecker-status=\"valid\" data-mce-style=\"list-style-type: none;\" data-mce-href=\"../../../i/pomada-xilocaina-principais-usos\">Pomada xilocaína: principais usos</a></p><p style=\"list-style-type: none;\" data-mce-style=\"list-style-type: none;\"><a style=\"list-style-type: none;\" title=\"Seringa de insulina Descarpack\" href=\"/i/seringa-de-insulina-descarpack\" data-mce-linkchecker-status=\"valid\" data-mce-style=\"list-style-type: none;\" data-mce-href=\"../../../i/seringa-de-insulina-descarpack\">Seringa de insulina Descarpack</a></p><p style=\"list-style-type: none;\" data-mce-style=\"list-style-type: none;\"><a style=\"list-style-type: none;\" title=\"Tipos de fios de sutura\" href=\"/i/tipos-de-fios-de-sutura\" data-mce-linkchecker-status=\"valid\" data-mce-style=\"list-style-type: none;\" data-mce-href=\"../../../i/tipos-de-fios-de-sutura\">Tipos de fios de sutura</a></p><p style=\"list-style-type: none;\" data-mce-style=\"list-style-type: none;\"><a style=\"list-style-type: none;\" title=\"Qual a diferença entre sondas hospitalares, drenos e cateteres?\" href=\"/i/diferenca-sondas-hospitalares-drenos-e-cateteres\" data-mce-linkchecker-status=\"valid\" data-mce-style=\"list-style-type: none;\" data-mce-href=\"../../../i/diferenca-sondas-hospitalares-drenos-e-cateteres\">Qual a diferença entre sondas hospitalares, drenos e cateteres?</a></p><p style=\"list-style-type: none;\" data-mce-style=\"list-style-type: none;\"><a style=\"list-style-type: none;\" title=\"Dieta enteral por sonda hospitalar: como funciona?\" href=\"/i/dieta-enteral-por-sonda-hospitalar-como-funciona\" data-mce-linkchecker-status=\"valid\" data-mce-style=\"list-style-type: none;\" data-mce-href=\"../../../i/dieta-enteral-por-sonda-hospitalar-como-funciona\">Dieta enteral por sonda hospitalar: como funciona?</a></p><p style=\"list-style-type: none;\" data-mce-style=\"list-style-type: none;\"><a style=\"list-style-type: none;\" title=\"Melhor marca de balança digital\" href=\"/i/melhor-marca-de-balanca-digital\" data-mce-linkchecker-status=\"valid\" data-mce-style=\"list-style-type: none;\" data-mce-href=\"../../../i/melhor-marca-de-balanca-digital\">Melhor marca de balança digital</a></p><p style=\"list-style-type: none;\" data-mce-style=\"list-style-type: none;\"><a style=\"list-style-type: none;\" title=\"Melhor marca de medidor de glicose\" href=\"/i/melhor-marca-de-medidor-de-glicose\" data-mce-linkchecker-status=\"valid\" data-mce-style=\"list-style-type: none;\" data-mce-href=\"../../../i/melhor-marca-de-medidor-de-glicose\">Melhor marca de medidor de glicose</a></p><p style=\"list-style-type: none;\" data-mce-style=\"list-style-type: none;\"><a style=\"list-style-type: none;\" title=\"Cateter intravenoso jelco: para que serve? Onde comprar?\" href=\"/i/cateter-intravenoso-jelco-para-que-serve\" data-mce-linkchecker-status=\"valid\" data-mce-style=\"list-style-type: none;\" data-mce-href=\"../../../i/cateter-intravenoso-jelco-para-que-serve\">Cateter intravenoso jelco: para que serve? Onde comprar?</a></p><p style=\"list-style-type: none;\" data-mce-style=\"list-style-type: none;\"><a style=\"list-style-type: none;\" title=\"O que é scalp?\" href=\"/i/o-que-e-scalp\" data-mce-linkchecker-status=\"valid\" data-mce-style=\"list-style-type: none;\" data-mce-href=\"../../../i/o-que-e-scalp\">O que é scalp?</a></p><p style=\"list-style-type: none;\" data-mce-style=\"list-style-type: none;\"><a style=\"list-style-type: none;\" title=\"Onde comprar tela de Marlex em polipropileno?\" href=\"/i/onde-comprar-tela-de-marlex-em-polipropileno\" data-mce-linkchecker-status=\"valid\" data-mce-style=\"list-style-type: none;\" data-mce-href=\"../../../i/onde-comprar-tela-de-marlex-em-polipropileno\">Onde comprar tela de Marlex em polipropileno?</a></p><p style=\"list-style-type: none;\" data-mce-style=\"list-style-type: none;\"><a style=\"list-style-type: none;\" title=\"Onde comprar Prometazina 50 mg injetável?\" href=\"/i/onde-comprar-prometazina-50-mg-injetavel\" data-mce-linkchecker-status=\"valid\" data-mce-style=\"list-style-type: none;\" data-mce-href=\"../../../i/onde-comprar-prometazina-50-mg-injetavel\">Onde comprar Prometazina 50 mg injetável?</a></p><p style=\"list-style-type: none;\" data-mce-style=\"list-style-type: none;\"><a style=\"list-style-type: none;\" title=\"Sulfato de amicacina Novamin: uso em hospital\" href=\"/i/sulfato-de-amicacina-novamin-uso-em-hospital\" data-mce-linkchecker-status=\"valid\" data-mce-style=\"list-style-type: none;\" data-mce-href=\"../../../i/sulfato-de-amicacina-novamin-uso-em-hospital\">Sulfato de amicacina Novamin: uso em hospital</a></p><p style=\"list-style-type: none;\" data-mce-style=\"list-style-type: none;\"><a style=\"list-style-type: none;\" title=\"Gentamicina injetável: uso hospitalar\" href=\"/i/gentamicina-injetavel-uso-hospitalar\" data-mce-linkchecker-status=\"valid\" data-mce-style=\"list-style-type: none;\" data-mce-href=\"../../../i/gentamicina-injetavel-uso-hospitalar\">Gentamicina injetável: uso hospitalar</a></p><p style=\"list-style-type: none;\" data-mce-style=\"list-style-type: none;\"><a style=\"list-style-type: none;\" title=\"Cetoprofeno Injetável: como aplicar?\" href=\"/i/cetoprofeno-injetavel-como-aplicar\" data-mce-linkchecker-status=\"valid\" data-mce-style=\"list-style-type: none;\" data-mce-href=\"../../../i/cetoprofeno-injetavel-como-aplicar\">Cetoprofeno Injetável: como aplicar?</a></p><p style=\"list-style-type: none;\" data-mce-style=\"list-style-type: none;\"><a style=\"list-style-type: none;\" title=\"Sonda Retal: função no enteroclisma\" href=\"/i/sonda-retal-funcao-no-enteroclisma\" data-mce-linkchecker-status=\"valid\" data-mce-style=\"list-style-type: none;\" data-mce-href=\"../../../i/sonda-retal-funcao-no-enteroclisma\">Sonda Retal: função no enteroclisma</a></p><p style=\"list-style-type: none;\" data-mce-style=\"list-style-type: none;\"><a style=\"list-style-type: none;\" title=\"Enoxaparina 40 mg: comprar com distribuidor de medicamentos\" href=\"/i/enoxaparina-comprar-com-distribuidor-medicamentos\" data-mce-linkchecker-status=\"valid\" data-mce-style=\"list-style-type: none;\" data-mce-href=\"../../../i/enoxaparina-comprar-com-distribuidor-medicamentos\">Enoxaparina 40 mg: comprar com distribuidor de medicamentos</a></p><p style=\"list-style-type: none;\" data-mce-style=\"list-style-type: none;\"><a style=\"list-style-type: none;\" title=\"Kit de enfermagem para estudantes\" href=\"/i/kit-de-enfermagem-para-estudantes\" data-mce-linkchecker-status=\"valid\" data-mce-style=\"list-style-type: none;\" data-mce-href=\"../../../i/kit-de-enfermagem-para-estudantes\">Kit de enfermagem para estudantes</a></p><p style=\"list-style-type: none;\" data-mce-style=\"list-style-type: none;\"><a style=\"list-style-type: none;\" title=\"Sonda de aspiração traqueal: comprar para hospital\" href=\"/i/sonda-de-aspiracao-traqueal-comprar-para-hospital\" data-mce-linkchecker-status=\"valid\" data-mce-style=\"list-style-type: none;\" data-mce-href=\"../../../i/sonda-de-aspiracao-traqueal-comprar-para-hospital\">Sonda de aspiração traqueal: comprar para hospital</a></p><p style=\"list-style-type: none;\" data-mce-style=\"list-style-type: none;\"><a style=\"list-style-type: none;\" title=\"Glicose hipertônica: uso hospitalar\" href=\"/i/glicose-hipertonica-uso-hospitalar\" data-mce-linkchecker-status=\"valid\" data-mce-style=\"list-style-type: none;\" data-mce-href=\"../../../i/glicose-hipertonica-uso-hospitalar\">Glicose hipertônica: uso hospitalar</a></p><p style=\"list-style-type: none;\" data-mce-style=\"list-style-type: none;\"><a style=\"list-style-type: none;\" title=\"Sonda para gastrostomia: uso em hospitais\" href=\"/i/sonda-para-gastrostomia-uso-em-hospitais\" data-mce-linkchecker-status=\"valid\" data-mce-style=\"list-style-type: none;\" data-mce-href=\"../../../i/sonda-para-gastrostomia-uso-em-hospitais\">Sonda para gastrostomia: uso em hospitais</a></p><p style=\"list-style-type: none;\" data-mce-style=\"list-style-type: none;\"><a style=\"list-style-type: none;\" title=\"Nutrição enteral: tipo de sonda\" href=\"/i/nutricao-enteral-tipo-de-sonda\" data-mce-linkchecker-status=\"valid\" data-mce-style=\"list-style-type: none;\" data-mce-href=\"../../../i/nutricao-enteral-tipo-de-sonda\">Nutrição enteral: tipo de sonda</a></p><p style=\"list-style-type: none;\" data-mce-style=\"list-style-type: none;\"><a style=\"list-style-type: none;\" title=\"Kit de enfermagem: quais os itens obrigatórios?\" href=\"/i/kit-de-enfermagem-quais-os-itens-obrigatorios\" data-mce-linkchecker-status=\"valid\" data-mce-style=\"list-style-type: none;\" data-mce-href=\"../../../i/kit-de-enfermagem-quais-os-itens-obrigatorios\">Kit de enfermagem: quais os itens obrigatórios?</a></p><p style=\"list-style-type: none;\" data-mce-style=\"list-style-type: none;\"><a style=\"list-style-type: none;\" title=\"Kit de sutura: quais os itens obrigatórios\" href=\"/i/kit-de-sutura-quais-os-itens-obrigatorios\" data-mce-linkchecker-status=\"valid\" data-mce-style=\"list-style-type: none;\" data-mce-href=\"../../../i/kit-de-sutura-quais-os-itens-obrigatorios\">Kit de sutura: quais os itens obrigatórios</a></p><p style=\"list-style-type: none;\" data-mce-style=\"list-style-type: none;\"><a style=\"list-style-type: none;\" title=\"Coleta de sangue: tipos e materiais necessários\" href=\"/i/coleta-de-sangue-tipos-e-materiais-necessarios\" data-mce-linkchecker-status=\"valid\" data-mce-style=\"list-style-type: none;\" data-mce-href=\"../../../i/coleta-de-sangue-tipos-e-materiais-necessarios\">Coleta de sangue: tipos e materiais necessários</a></p><p style=\"list-style-type: none;\" data-mce-style=\"list-style-type: none;\"><a style=\"list-style-type: none;\" title=\"Distribuidora de medicamentos hospitalares\" href=\"/i/distribuidora-de-medicamentos-hospitalares\" data-mce-linkchecker-status=\"valid\" data-mce-style=\"list-style-type: none;\" data-mce-href=\"../../../i/distribuidora-de-medicamentos-hospitalares\">Distribuidora de medicamentos hospitalares</a></p><p style=\"list-style-type: none;\" data-mce-style=\"list-style-type: none;\"><a style=\"list-style-type: none;\" title=\"Complexo B injetável: uso hospitalar\" href=\"/i/complexo-b-injetavel-uso-hospitalar\" data-mce-linkchecker-status=\"valid\" data-mce-style=\"list-style-type: none;\" data-mce-href=\"../../../i/complexo-b-injetavel-uso-hospitalar\">Complexo B injetável: uso hospitalar</a></p><p style=\"list-style-type: none;\" data-mce-style=\"list-style-type: none;\"><a style=\"list-style-type: none;\" title=\"Ceftriaxona injetável: como diluir e administrar?\" href=\"/i/ceftriaxona-injetavel-como-diluir-e-administrar\" data-mce-linkchecker-status=\"valid\" data-mce-style=\"list-style-type: none;\" data-mce-href=\"../../../i/ceftriaxona-injetavel-como-diluir-e-administrar\">Ceftriaxona injetável: como diluir e administrar?</a></p><p style=\"list-style-type: none;\" data-mce-style=\"list-style-type: none;\"><a style=\"list-style-type: none;\" title=\"Propofol: anestésico intravenoso. Quais os efeitos colaterais?\" href=\"/i/propofol-anestesico-intravenoso-efeitos-colaterais\" data-mce-linkchecker-status=\"valid\" data-mce-style=\"list-style-type: none;\" data-mce-href=\"../../../i/propofol-anestesico-intravenoso-efeitos-colaterais\">Propofol: anestésico intravenoso. Quais os efeitos colaterais?</a></p><p style=\"list-style-type: none;\" data-mce-style=\"list-style-type: none;\"><a style=\"list-style-type: none;\" title=\"Sulfato de Terbutalina: como administrar\" href=\"/i/sulfato-de-terbutalina-como-administrar\" data-mce-linkchecker-status=\"valid\" data-mce-style=\"list-style-type: none;\" data-mce-href=\"../../../i/sulfato-de-terbutalina-como-administrar\">Sulfato de Terbutalina: como administrar</a></p><p style=\"list-style-type: none;\" data-mce-style=\"list-style-type: none;\"><a style=\"list-style-type: none;\" title=\"Sonda hospitalar: quais os tipos?\" href=\"/i/sonda-hospitalar-quais-os-tipos\" data-mce-linkchecker-status=\"valid\" data-mce-style=\"list-style-type: none;\" data-mce-href=\"../../../i/sonda-hospitalar-quais-os-tipos\">Sonda hospitalar: quais os tipos?</a></p><p style=\"list-style-type: none;\" data-mce-style=\"list-style-type: none;\"><a style=\"list-style-type: none;\" title=\"Tipos de cateter intravenoso\" href=\"/i/tipos-de-cateter-intravenoso\" data-mce-linkchecker-status=\"valid\" data-mce-style=\"list-style-type: none;\" data-mce-href=\"../../../i/tipos-de-cateter-intravenoso\">Tipos de cateter intravenoso</a></p><p style=\"list-style-type: none;\" data-mce-style=\"list-style-type: none;\"><a style=\"list-style-type: none;\" title=\"Pomada Xilocaína: para que serve?\" href=\"/i/pomada-xilocaina-para-que-serve\" data-mce-linkchecker-status=\"valid\" data-mce-style=\"list-style-type: none;\" data-mce-href=\"../../../i/pomada-xilocaina-para-que-serve\">Pomada Xilocaína: para que serve?</a></p><p style=\"list-style-type: none;\" data-mce-style=\"list-style-type: none;\"><a style=\"list-style-type: none;\" title=\"Hidrocortisona injetável: o que é? Para que serve?\" href=\"/i/hidrocortisona-injetavel-o-que-e-para-que-serve\" data-mce-linkchecker-status=\"valid\" data-mce-style=\"list-style-type: none;\" data-mce-href=\"../../../i/hidrocortisona-injetavel-o-que-e-para-que-serve\">Hidrocortisona injetável: o que é? Para que serve?</a></p><p style=\"list-style-type: none;\" data-mce-style=\"list-style-type: none;\"><a style=\"list-style-type: none;\" title=\"Coleta de sangue venoso: passo a passo\" href=\"/i/coleta-de-sangue-venoso-passo-a-passo\" data-mce-linkchecker-status=\"valid\" data-mce-style=\"list-style-type: none;\" data-mce-href=\"../../../i/coleta-de-sangue-venoso-passo-a-passo\">Coleta de sangue venoso: passo a passo</a></p><p style=\"list-style-type: none;\" data-mce-style=\"list-style-type: none;\"><a style=\"list-style-type: none;\" title=\"Scalp e cateter: entenda a diferença entre eles\" href=\"/i/scalp-e-cateter-entenda-a-diferenca-entre-eles\" data-mce-linkchecker-status=\"valid\" data-mce-style=\"list-style-type: none;\" data-mce-href=\"../../../i/scalp-e-cateter-entenda-a-diferenca-entre-eles\">Scalp e cateter: entenda a diferença entre eles</a></p><p style=\"list-style-type: none;\" data-mce-style=\"list-style-type: none;\"><a style=\"list-style-type: none;\" title=\"Clorpromazina: indicações e onde comprar\" href=\"/i/clorpromazina-indicacoes-e-onde-comprar\" data-mce-linkchecker-status=\"valid\" data-mce-style=\"list-style-type: none;\" data-mce-href=\"../../../i/clorpromazina-indicacoes-e-onde-comprar\">Clorpromazina: indicações e onde comprar</a></p><p style=\"list-style-type: none;\" data-mce-style=\"list-style-type: none;\"><a style=\"list-style-type: none;\" title=\"Negatoscópio de Parede: dicas para escolher\" href=\"/i/negatoscopio-de-parede-dicas-para-escolher\" data-mce-linkchecker-status=\"valid\" data-mce-style=\"list-style-type: none;\" data-mce-href=\"../../../i/negatoscopio-de-parede-dicas-para-escolher\">Negatoscópio de Parede: dicas para escolher</a></p><p style=\"list-style-type: none;\" data-mce-style=\"list-style-type: none;\"><a style=\"list-style-type: none;\" title=\"Medicamentos injetáveis para farmácia hospitalar\" href=\"/i/medicamentos-injetaveis-para-farmacia-hospitalar\" data-mce-linkchecker-status=\"valid\" data-mce-style=\"list-style-type: none;\" data-mce-href=\"../../../i/medicamentos-injetaveis-para-farmacia-hospitalar\">Medicamentos injetáveis para farmácia hospitalar</a></p><p style=\"list-style-type: none;\" data-mce-style=\"list-style-type: none;\"><a style=\"list-style-type: none;\" title=\"Gluconato de Cálcio: comprar em distribuidora de medicamentos\" href=\"/i/gluconato-de-calcio-comprar-em-distribuidora\" data-mce-linkchecker-status=\"valid\" data-mce-style=\"list-style-type: none;\" data-mce-href=\"../../../i/gluconato-de-calcio-comprar-em-distribuidora\">Gluconato de Cálcio: comprar em distribuidora de medicamentos</a></p><p style=\"list-style-type: none;\" data-mce-style=\"list-style-type: none;\"><a style=\"list-style-type: none;\" title=\"Xilocaína e lidocaína são o mesmo medicamento. Como comprar?\" href=\"/i/xilocaina-e-lidocaina-sao-o-mesmo-medicamento\" data-mce-linkchecker-status=\"valid\" data-mce-style=\"list-style-type: none;\" data-mce-href=\"../../../i/xilocaina-e-lidocaina-sao-o-mesmo-medicamento\">Xilocaína e lidocaína são o mesmo medicamento. Como comprar?</a></p><p style=\"list-style-type: none;\" data-mce-style=\"list-style-type: none;\"><a style=\"list-style-type: none;\" title=\"Lâmina de bisturi: tipos, usos e onde comprar\" href=\"/i/lamina-de-bisturi-tipos-usos-e-onde-comprar\" data-mce-linkchecker-status=\"valid\" data-mce-style=\"list-style-type: none;\" data-mce-href=\"../../../i/lamina-de-bisturi-tipos-usos-e-onde-comprar\">Lâmina de bisturi: tipos, usos e onde comprar</a></p><p style=\"list-style-type: none;\" data-mce-style=\"list-style-type: none;\"><a style=\"list-style-type: none;\" title=\"Sulfato de magnésio: para que serve e como administrar\" href=\"/i/sulfato-de-magnesio-para-que-serve\" data-mce-linkchecker-status=\"valid\" data-mce-style=\"list-style-type: none;\" data-mce-href=\"../../../i/sulfato-de-magnesio-para-que-serve\">Sulfato de magnésio: para que serve e como administrar</a></p><p style=\"list-style-type: none;\" data-mce-style=\"list-style-type: none;\"><a style=\"list-style-type: none;\" title=\"Produtos hospitalares: como comprar com segurança\" href=\"/i/produtos-hospitalares-como-comprar-com-seguranca\" data-mce-linkchecker-status=\"valid\" data-mce-style=\"list-style-type: none;\" data-mce-href=\"../../../i/produtos-hospitalares-como-comprar-com-seguranca\">Produtos hospitalares: como comprar com segurança</a></p><p style=\"list-style-type: none;\" data-mce-style=\"list-style-type: none;\"><a style=\"list-style-type: none;\" title=\"Kit acadêmico de enfermagem\" href=\"/i/kit-academico-de-enfermagem\" data-mce-linkchecker-status=\"valid\" data-mce-style=\"list-style-type: none;\" data-mce-href=\"../../../i/kit-academico-de-enfermagem\">Kit acadêmico de enfermagem</a></p><p style=\"list-style-type: none;\" data-mce-style=\"list-style-type: none;\"><a style=\"list-style-type: none;\" title=\"Termômetro digital hospitalar: melhor custo-benefício\" href=\"/i/termometro-digital-hospitalar-custo-beneficio\" data-mce-linkchecker-status=\"valid\" data-mce-style=\"list-style-type: none;\" data-mce-href=\"../../../i/termometro-digital-hospitalar-custo-beneficio\">Termômetro digital hospitalar: melhor custo-benefício</a></p><p style=\"list-style-type: none;\" data-mce-style=\"list-style-type: none;\"><a style=\"list-style-type: none;\" title=\"Coronavírus: sintomas e prevenção\" href=\"/i/coronavirus-sintomas-e-prevencao\" data-mce-linkchecker-status=\"valid\" data-mce-style=\"list-style-type: none;\" data-mce-href=\"../../../i/coronavirus-sintomas-e-prevencao\">Coronavírus: sintomas e prevenção</a></p><p style=\"list-style-type: none;\" data-mce-style=\"list-style-type: none;\"><a style=\"list-style-type: none;\" title=\"Álcool gel: qual o tipo certo para matar vírus?\" href=\"/i/alcool-gel-qual-o-tipo-certo-para-matar-virus\" data-mce-linkchecker-status=\"valid\" data-mce-style=\"list-style-type: none;\" data-mce-href=\"../../../i/alcool-gel-qual-o-tipo-certo-para-matar-virus\">Álcool gel: qual o tipo certo para matar vírus?</a></p><p style=\"list-style-type: none;\" data-mce-style=\"list-style-type: none;\"><a style=\"list-style-type: none;\" title=\"Oxímetro pode diagnosticar coronavírus?\" href=\"/i/oximetro-pode-diagnosticar-coronavirus\" data-mce-linkchecker-status=\"valid\" data-mce-style=\"list-style-type: none;\" data-mce-href=\"../../../i/oximetro-pode-diagnosticar-coronavirus\">Oxímetro pode diagnosticar coronavírus?</a></p><p style=\"list-style-type: none;\" data-mce-style=\"list-style-type: none;\"><a style=\"list-style-type: none;\" title=\"EPI hospitalar: quais os principais equipamentos para proteção contra o coronavírus?\" href=\"/i/equipamentos-para-protecao-contra-o-coronavirus\" data-mce-linkchecker-status=\"valid\" data-mce-style=\"list-style-type: none;\" data-mce-href=\"../../../i/equipamentos-para-protecao-contra-o-coronavirus\">EPI hospitalar: quais os principais equipamentos para proteção contra o coronavírus?</a></p><p style=\"list-style-type: none;\" data-mce-style=\"list-style-type: none;\"><a style=\"list-style-type: none;\" title=\"Como medir febre com termômetro digital?\" href=\"/i/como-medir-febre-com-termometro-digital\" data-mce-linkchecker-status=\"valid\" data-mce-style=\"list-style-type: none;\" data-mce-href=\"../../../i/como-medir-febre-com-termometro-digital\">Como medir febre com termômetro digital?</a></p><p style=\"list-style-type: none;\" data-mce-style=\"list-style-type: none;\"><a style=\"list-style-type: none;\" title=\"Álcool em gel 70% ou álcool líquido? Quando usar cada um?\" href=\"/i/alcool-em-gel-70-ou-alcool-liquido-quando-usar\" data-mce-linkchecker-status=\"valid\" data-mce-style=\"list-style-type: none;\" data-mce-href=\"../../../i/alcool-em-gel-70-ou-alcool-liquido-quando-usar\">Álcool em gel 70% ou álcool líquido? Quando usar cada um?</a></p><p style=\"list-style-type: none;\" data-mce-style=\"list-style-type: none;\"><a style=\"list-style-type: none;\" title=\"Oxímetro g-tech: como funciona?\" href=\"/i/oximetro-g-tech-como-funciona\" data-mce-linkchecker-status=\"valid\" data-mce-style=\"list-style-type: none;\" data-mce-href=\"../../../i/oximetro-g-tech-como-funciona\">Oxímetro g-tech: como funciona?</a></p><p style=\"list-style-type: none;\" data-mce-style=\"list-style-type: none;\"><a style=\"list-style-type: none;\" title=\"Hidrocortisona: diluição e posologia\" href=\"/i/hidrocortisona-diluicao-e-posologia\" data-mce-linkchecker-status=\"valid\" data-mce-style=\"list-style-type: none;\" data-mce-href=\"../../../i/hidrocortisona-diluicao-e-posologia\">Hidrocortisona: diluição e posologia</a></p><p style=\"list-style-type: none;\" data-mce-style=\"list-style-type: none;\"><a style=\"list-style-type: none;\" title=\"Xilocaína para tatuagem: pode usar?\" href=\"/i/xilocaina-para-tatuagem-pode-usar\" data-mce-linkchecker-status=\"valid\" data-mce-style=\"list-style-type: none;\" data-mce-href=\"../../../i/xilocaina-para-tatuagem-pode-usar\">Xilocaína para tatuagem: pode usar?</a></p><p style=\"list-style-type: none;\" data-mce-style=\"list-style-type: none;\"><a style=\"list-style-type: none;\" title=\"Álcool em gel 70° spray: funciona?\" href=\"/i/alcool-em-gel-70-spray-funciona\" data-mce-linkchecker-status=\"valid\" data-mce-style=\"list-style-type: none;\" data-mce-href=\"../../../i/alcool-em-gel-70-spray-funciona\">Álcool em gel 70° spray: funciona?</a></p><p style=\"list-style-type: none;\" data-mce-style=\"list-style-type: none;\"><a style=\"list-style-type: none;\" href=\"/i/qual-a-diferenca-entre-o-estetoscopio-spirit-pro-l\" data-mce-linkchecker-status=\"valid\" data-mce-style=\"list-style-type: none;\" data-mce-href=\"../../../i/qual-a-diferenca-entre-o-estetoscopio-spirit-pro-l\">Qual a diferença entre o Estetoscópio Spirit Pro-Lite e o Professional?</a></p><p style=\"list-style-type: none;\" data-mce-style=\"list-style-type: none;\"><a style=\"list-style-type: none;\" href=\"/i/scalps-indicados-para-coleta-de-sangue\" data-mce-linkchecker-status=\"valid\" data-mce-style=\"list-style-type: none;\" data-mce-href=\"../../../i/scalps-indicados-para-coleta-de-sangue\">Scalps indicados para coleta de sangue</a></p><p style=\"list-style-type: none;\" data-mce-style=\"list-style-type: none;\"><a style=\"list-style-type: none;\" href=\"/i/a-importancia-dos-cateteres-no-tratamento-de-pacie\" data-mce-linkchecker-status=\"valid\" data-mce-style=\"list-style-type: none;\" data-mce-href=\"../../../i/a-importancia-dos-cateteres-no-tratamento-de-pacie\">A importância dos cateteres no tratamento de pacientes com COVID-19</a></p><p style=\"list-style-type: none;\" data-mce-style=\"list-style-type: none;\"><a style=\"list-style-type: none;\" href=\"/i/compressas-de-gaze\" data-mce-linkchecker-status=\"valid\" data-mce-style=\"list-style-type: none;\" data-mce-href=\"../../../i/compressas-de-gaze\">Compressas de gaze</a></p>"
            }
          },
          "verticalSpacing": "top",
          "withContainer": true
        }
      ]
    },
    {
      "__resolveType": "Footer Global"
    }
  ],
  "__resolveType": "$live/pages/LivePage.tsx"
}